nornir_conditional_runner/__init__.py
nornir_conditional_runner/conditional_runner.py
nornir_conditional_runner-0.1.6.dist-info/LICENSE.txt
nornir_conditional_runner-0.1.6.dist-info/METADATA
nornir_conditional_runner-0.1.6.dist-info/WHEEL
nornir_conditional_runner-0.1.6.dist-info/entry_points.txt
nornir_conditional_runner-0.1.6.dist-info/RECORD
