Metadata-Version: 2.1
Name: nornir-conditional-runner
Version: 0.1.6
Summary: A Nornir plugin enforcing concurrency limits based on device groups
Home-page: https://github.com/InfrastructureAsCode-ch/nornir_conditional_runner
Author: simon linder
Author-email: simon.linder@ost.ch
Requires-Python: >=3.8,<4.0
Classifier: Programming Language :: Python :: 3
Classifier: Programming Language :: Python :: 3.8
Classifier: Programming Language :: Python :: 3.9
Classifier: Programming Language :: Python :: 3.10
Classifier: Programming Language :: Python :: 3.11
Classifier: Programming Language :: Python :: 3.12
Classifier: Programming Language :: Python :: 3.13
Requires-Dist: nornir (>=3,<4)
Requires-Dist: setuptools ; python_version >= "3.12"
Project-URL: Repository, https://github.com/InfrastructureAsCode-ch/nornir_conditional_runner
